LICENSE.md
MANIFEST.in
README.rst
pyproject.toml
requirements.core.txt
requirements.txt
setup.py
core_federated_search_app/__init__.py
core_federated_search_app/admin.py
core_federated_search_app/apps.py
core_federated_search_app/menus.py
core_federated_search_app/settings.py
core_federated_search_app/urls.py
core_federated_search_app.egg-info/PKG-INFO
core_federated_search_app.egg-info/SOURCES.txt
core_federated_search_app.egg-info/dependency_links.txt
core_federated_search_app.egg-info/requires.txt
core_federated_search_app.egg-info/top_level.txt
core_federated_search_app/commons/__init__.py
core_federated_search_app/commons/exceptions.py
core_federated_search_app/components/__init__.py
core_federated_search_app/components/instance/__init__.py
core_federated_search_app/components/instance/api.py
core_federated_search_app/components/instance/models.py
core_federated_search_app/migrations/0001_initial.py
core_federated_search_app/migrations/0002_optional_instance_auth.py
core_federated_search_app/migrations/__init__.py
core_federated_search_app/rest/__init__.py
core_federated_search_app/rest/urls.py
core_federated_search_app/rest/instance/__init__.py
core_federated_search_app/rest/instance/serializers.py
core_federated_search_app/rest/instance/views.py
core_federated_search_app/static/core_federated_search_app/admin/css/repositories.css
core_federated_search_app/static/core_federated_search_app/admin/css/add/form.css
core_federated_search_app/static/core_federated_search_app/admin/js/repositories/add/form.js
core_federated_search_app/static/core_federated_search_app/admin/js/repositories/list/modals/delete.js
core_federated_search_app/static/core_federated_search_app/admin/js/repositories/list/modals/delete.raw.js
core_federated_search_app/static/core_federated_search_app/admin/js/repositories/list/modals/refresh.js
core_federated_search_app/static/core_federated_search_app/admin/js/repositories/list/modals/refresh.raw.js
core_federated_search_app/templates/core_federated_search_app/admin/repositories/add_repository.html
core_federated_search_app/templates/core_federated_search_app/admin/repositories/list_repositories.html
